[
    {
        "name": "Main asteroid belt",
        "variableName": "mainAsteroidBelt",
        "minDistanceX": 6,
        "minDistanceY": 4.5,
        "radius": 0.4,
        "nbAsteroids": 200,
        "textures": ["asteroid1.jpg", "asteroid2.jpg"],
        "informations": {
            "location": "Entre les orbites de Mars et Jupiter",
            "composition": ["Roches", "Silicate" , "Nickel" , "Fer", "Carbone", "Métaux", "Hydrates"],
            "numberOfAsteroids": "Plus d'un million d'objets répertoriés",
            "caracteristics": [
              "La Ceinture d'astéroïdes principale est une région dense d'astéroïdes et de petits objets orbitant autour du Soleil.",
              "La plupart des astéroïdes de la ceinture sont relativement petits, bien que certains puissent atteindre des tailles considérables.",
              "Ces astéroïdes sont des restes de la formation du système solaire il y a des milliards d'années."
            ]
        }
    },
    {
        "name": "Kuiper belt",
        "variableName": "kuiperBelt",
        "minDistanceX": 20,
        "minDistanceY": 16.5,
        "radius": 1.5,
        "nbAsteroids": 500,
        "textures": ["kuiper_asteroid1.jpg", "kuiper_asteroid2.jpg"],
        "informations": {
            "location": "Au-delà de l'orbite de Neptune",
            "composition": ["Objets glacés", "Eau" , "Méthane", "Azote", "Roches",  "Poussières"],
            "numberOfAsteroids": "Des milliards d'objets, y compris des planètes naines, des comètes et des astéroïdes glacés.",
            "caracteristics": [
              "La Ceinture de Kuiper est une région étendue du système solaire au-delà de l'orbite de Neptune.",
              "Elle contient une grande variété d'objets glacés, dont certains sont considérés comme des planètes naines, tels que Pluton, Éris et Makémaké.",
              "La Ceinture de Kuiper est une source importante de comètes qui entrent périodiquement dans le système solaire interne."
            ]
        }
    }
]